airflow_mcp_hipposys/__init__.py
airflow_mcp_hipposys/mcp_airflow.py
airflow_mcp_hipposys-0.1.0a12.dist-info/LICENSE
airflow_mcp_hipposys-0.1.0a12.dist-info/METADATA
airflow_mcp_hipposys-0.1.0a12.dist-info/WHEEL
airflow_mcp_hipposys-0.1.0a12.dist-info/RECORD
