Metadata-Version: 2.3
Name: airflow-mcp-hipposys
Version: 0.1.0a12
Summary: An MCP server for Apache Airflow that enables non-technical users to interact with Apache Airflow workflows through natural language.
License: MIT
Author: Hipposys
Requires-Python: >=3.10,<4.0
Classifier: License :: OSI Approved :: MIT License
Classifier: Programming Language :: Python :: 3
Classifier: Programming Language :: Python :: 3.10
Classifier: Programming Language :: Python :: 3.11
Classifier: Programming Language :: Python :: 3.12
Classifier: Programming Language :: Python :: 3.13
Requires-Dist: fastapi (<=0.115.12)
Requires-Dist: httpx (<=0.28.1)
Requires-Dist: mcp[cli] (<2.0)
Requires-Dist: starlette (<=0.46.2)
Requires-Dist: uvicorn (<=0.34.3)
Project-URL: homepage, https://github.com/hipposys-ltd/airflow-mcp
